easy_server/__init__.py
easy_server/_server.py
easy_server/_server_file.py
easy_server/_vault_file.py
easy_server/_version.py
easy_server-0.8.0.dist-info/LICENSE
easy_server-0.8.0.dist-info/METADATA
easy_server-0.8.0.dist-info/WHEEL
easy_server-0.8.0.dist-info/top_level.txt
easy_server-0.8.0.dist-info/zip-safe
easy_server-0.8.0.dist-info/RECORD
